{
    "_key": "!items!a1b2c3d4e5f60006",
    "_id": "a1b2c3d4e5f60006",
    "name": "Fresh Meat",
    "type": "consumable",
    "img": "icons/consumables/meat/steak-raw-red-pink.webp",
    "system": {
        "description": {
            "value": "<p>A cut of raw game meat from a recent hunt. Needs cooking before it is safe to eat.</p>"
        },
        "rarity": "common",
        "weight": 1,
        "price": {
            "value": 5,
            "denomination": "cp"
        },
        "type": {
            "value": "food",
            "subtype": ""
        }
    },
    "folder": "hun71n6000000001",
    "flags": {
        "ionrift-respite": {
            "itemRef": "fresh_meat",
            "terrain": "any",
            "category": "hunt",
            "foodTag": "raw_meat",
            "spoilsAfter": 2
        }
    },
    "effects": [],
    "ownership": {
        "default": 0
    },
    "sort": 600
}
